airflow/providers/siasg/__init__.py
airflow/providers/siasg/provider.yaml
airflow/providers/siasg/dw/__init__.py
airflow/providers/siasg/dw/hooks/__init__.py
airflow/providers/siasg/dw/hooks/dw.py
airflow/providers/siasg/dw/transfers/__init__.py
airflow/providers/siasg/dw/transfers/relatorio_para_arquivo.py
airflow/providers/siasg/dw/transfers/relatorio_para_mongo.py
airflow/providers/siasg/example_dags/__init__.py
airflow/providers/siasg/example_dags/dw.py
build/lib/airflow/providers/siasg/__init__.py
build/lib/airflow/providers/siasg/dw/__init__.py
build/lib/airflow/providers/siasg/dw/hooks/__init__.py
build/lib/airflow/providers/siasg/dw/hooks/dw.py
build/lib/airflow/providers/siasg/dw/transfers/__init__.py
build/lib/airflow/providers/siasg/dw/transfers/relatorio_para_arquivo.py
build/lib/airflow/providers/siasg/dw/transfers/relatorio_para_mongo.py
build/lib/airflow/providers/siasg/example_dags/__init__.py
build/lib/airflow/providers/siasg/example_dags/dw.py
build/lib/build/lib/airflow/providers/siasg/__init__.py
build/lib/build/lib/airflow/providers/siasg/dw/__init__.py
build/lib/build/lib/airflow/providers/siasg/dw/hooks/__init__.py
build/lib/build/lib/airflow/providers/siasg/dw/hooks/dw.py
build/lib/build/lib/airflow/providers/siasg/dw/transfers/__init__.py
build/lib/build/lib/airflow/providers/siasg/dw/transfers/relatorio_para_arquivo.py
build/lib/build/lib/airflow/providers/siasg/dw/transfers/relatorio_para_mongo.py
build/lib/build/lib/airflow/providers/siasg/example_dags/__init__.py
build/lib/build/lib/airflow/providers/siasg/example_dags/dw.py
build/lib/build/lib/build/lib/airflow/providers/siasg/__init__.py
build/lib/build/lib/build/lib/airflow/providers/siasg/dw/__init__.py
build/lib/build/lib/build/lib/airflow/providers/siasg/dw/hooks/__init__.py
build/lib/build/lib/build/lib/airflow/providers/siasg/dw/hooks/dw.py
build/lib/build/lib/build/lib/airflow/providers/siasg/dw/transfers/__init__.py
airflow_providers_siasg-1.0.10.dist-info/METADATA
airflow_providers_siasg-1.0.10.dist-info/WHEEL
airflow_providers_siasg-1.0.10.dist-info/top_level.txt
airflow_providers_siasg-1.0.10.dist-info/RECORD
