Metadata-Version: 2.1
Name: airflow-providers-siasg
Version: 1.0.10
Summary: Provider para Airflow que comunica com SIASG e seus sistemas derivados
Home-page: UNKNOWN
Author: Carlos Alberto Duarte Pinto
Author-email: carlos.adpinto@gmail.com
License: MIT
Project-URL: Homepage, https://antigo.comprasgovernamentais.gov.br/index.php/comprasnet-siasg
Project-URL: Source Code, https://github.com/CarlosAdp/airflow-providers-siasg
Keywords: airflow,siasg,administracao,governo,compras,pregao
Platform: UNKNOWN
Classifier: Environment :: Console
Classifier: Environment :: Web Environment
Classifier: Intended Audience :: Developers
Classifier: Intended Audience :: System Administrators
Classifier: Programming Language :: Python :: 3.8
Classifier: Programming Language :: Python :: 3.9
Classifier: Topic :: Office/Business :: Financial :: Accounting
Requires-Dist: apache-airflow
Requires-Dist: requests
Requires-Dist: selenium-wire
Requires-Dist: humanize
Requires-Dist: pandas
Requires-Dist: apache-airflow[mongo]
Requires-Dist: openpyxl
